asl5000_utils/__init__.py
asl5000_utils/asl5000_utils.py
asl5000_utils-0.1.0.dist-info/LICENSE
asl5000_utils-0.1.0.dist-info/METADATA
asl5000_utils-0.1.0.dist-info/WHEEL
asl5000_utils-0.1.0.dist-info/top_level.txt
asl5000_utils-0.1.0.dist-info/RECORD
