Metadata-Version: 2.1
Name: asl5000-utils
Version: 0.1.0
Summary: A toolbox to extract data from the ASL5000
Home-page: https://github.com/deplanty/asl5000_utils
Author: deplanty
License: UNKNOWN
Platform: UNKNOWN
Classifier: Programming Language :: Python :: 3
Classifier: License :: OSI Approved :: GNU General Public License v3 (GPLv3)
Classifier: Operating System :: OS Independent
